adaptive_sdk/__init__.py
adaptive_sdk/base_client.py
adaptive_sdk/client.py
adaptive_sdk/error_handling.py
adaptive_sdk/openapi.json
adaptive_sdk/patch.py
adaptive_sdk/utils.py
adaptive_sdk/external/__init__.py
adaptive_sdk/external/base_model.py
adaptive_sdk/external/constants.py
adaptive_sdk/external/requests_journal.py
adaptive_sdk/external/reward_client.py
adaptive_sdk/external/reward_server.py
adaptive_sdk/external/reward_types.py
adaptive_sdk/external/websocket_utils.py
adaptive_sdk/graphql_client/__init__.py
adaptive_sdk/graphql_client/add_external_model.py
adaptive_sdk/graphql_client/add_hf_model.py
adaptive_sdk/graphql_client/add_model.py
adaptive_sdk/graphql_client/add_model_to_use_case.py
adaptive_sdk/graphql_client/add_remote_env.py
adaptive_sdk/graphql_client/async_base_client_open_telemetry.py
adaptive_sdk/graphql_client/async_client.py
adaptive_sdk/graphql_client/base_client_open_telemetry.py
adaptive_sdk/graphql_client/base_model.py
adaptive_sdk/graphql_client/base_operation.py
adaptive_sdk/graphql_client/cancel_ab_campaign.py
adaptive_sdk/graphql_client/cancel_job.py
adaptive_sdk/graphql_client/client.py
adaptive_sdk/graphql_client/create_ab_campaign.py
adaptive_sdk/graphql_client/create_custom_recipe.py
adaptive_sdk/graphql_client/create_dataset_from_multipart_upload.py
adaptive_sdk/graphql_client/create_grader.py
adaptive_sdk/graphql_client/create_job.py
adaptive_sdk/graphql_client/create_judge.py
adaptive_sdk/graphql_client/create_metric.py
adaptive_sdk/graphql_client/create_prebuilt_judge.py
adaptive_sdk/graphql_client/create_role.py
adaptive_sdk/graphql_client/create_team.py
adaptive_sdk/graphql_client/create_use_case.py
adaptive_sdk/graphql_client/create_user.py
adaptive_sdk/graphql_client/custom_fields.py
adaptive_sdk/graphql_client/custom_mutations.py
adaptive_sdk/graphql_client/custom_queries.py
adaptive_sdk/graphql_client/custom_typing_fields.py
adaptive_sdk/graphql_client/dataset_upload_processing_status.py
adaptive_sdk-0.12.0.dist-info/WHEEL
adaptive_sdk-0.12.0.dist-info/METADATA
adaptive_sdk-0.12.0.dist-info/RECORD
