Metadata-Version: 2.4
Name: adaptive-sdk
Version: 0.12.0
Summary: Python SDK for Adaptive Engine
Author-email: Vincent Debergue <vincent@adaptive-ml.com>, Joao Moura <joao@adaptive-ml.com>, Yacine Bouraoui <yacine@adaptive-ml.com>
Requires-Python: >=3.10
Requires-Dist: httpx >= 0.27.2
Requires-Dist: httpx-sse >= 0.4.0
Requires-Dist: gql >= 3.5.0
Requires-Dist: pydantic[email] >= 2.9.0
Requires-Dist: pyhumps >= 3.8.0
Requires-Dist: fastapi >= 0.121.2
Requires-Dist: uvicorn >= 0.34.0
Requires-Dist: jsonschema==4.24.0
Requires-Dist: websockets==15.0.1
Requires-Dist: types-jsonschema==4.23.0.20241208
Requires-Dist: loguru >= 0.7.0
Requires-Dist: hypothesis==6.138.2
Requires-Dist: hypothesis-jsonschema==0.23.1
Requires-Dist: portalocker >= 3.2.0
Requires-Dist: ariadne-codegen == 0.16.0 ; extra == "dev"
Requires-Dist: datamodel-code-generator == 0.34.0 ; extra == "dev"
Requires-Dist: astor >= 0.8.1 ; extra == "dev"
Requires-Dist: pdoc >= 15.0.1 ; extra == "dev"
Requires-Dist: toml>=0.10.2 ; extra == "dev"
Requires-Dist: black==25.1.0 ; extra == "dev"
Requires-Dist: pytest==8.4.1 ; extra == "dev"
Requires-Dist: pytest-asyncio==0.26.0 ; extra == "dev"
Requires-Dist: pytest-dependency==0.6.0 ; extra == "dev"
Requires-Dist: mypy==1.16.0 ; extra == "dev"
Requires-Dist: tenacity==9.1.2 ; extra == "dev"
Requires-Dist: pyright >= 1.1 ; extra == "dev"
Requires-Dist: adaptive-harmony ; extra == "dev"
Provides-Extra: dev
